hetzner_fireaccess_cleaner/__init__.py
hetzner_fireaccess_cleaner/hetzner_fireaccess_cleaner.py
hetzner_fireaccess_cleaner-0.0.1.dist-info/METADATA
hetzner_fireaccess_cleaner-0.0.1.dist-info/WHEEL
hetzner_fireaccess_cleaner-0.0.1.dist-info/entry_points.txt
hetzner_fireaccess_cleaner-0.0.1.dist-info/top_level.txt
hetzner_fireaccess_cleaner-0.0.1.dist-info/RECORD
