Metadata-Version: 2.1
Name: hetzner-fireaccess-cleaner
Version: 0.0.1
Summary: A simple CLI for cleaning automated access to hetzner firewalls
Home-page: https://gitlab.com/digitalarc/hetzner-fireaccess-cleaner
Author: DigitalArc Studio
License: MIT
Keywords: simple hetzner tools
Platform: UNKNOWN
Classifier: Environment :: Console
Classifier: Programming Language :: Python :: 3
Classifier: License :: OSI Approved :: MIT License
Requires-Python: >=3.6
Requires-Dist: toml (>=0.10.2)
Requires-Dist: click (>=8.0.0)
Requires-Dist: hcloud (>=1.16.0)
